main.py
setup.py
byteff.egg-info/PKG-INFO
byteff.egg-info/SOURCES.txt
byteff.egg-info/dependency_links.txt
byteff.egg-info/requires.txt
byteff.egg-info/top_level.txt